github_activity/__init__.py
github_activity/__main__.py
github_activity/api.py
github_activity/cache.py
github_activity/cli.py
github_activity/formatter.py
github_user_activity-0.2.0.dist-info/licenses/LICENSE
github_user_activity-0.2.0.dist-info/METADATA
github_user_activity-0.2.0.dist-info/WHEEL
github_user_activity-0.2.0.dist-info/entry_points.txt
github_user_activity-0.2.0.dist-info/top_level.txt
github_user_activity-0.2.0.dist-info/RECORD
